metaheuristicpy/__init__.py
metaheuristicpy/continous/__init__.py
metaheuristicpy/continous/benchmark_math/ArchimedesOptimizationAlgorithm.py
metaheuristicpy/continous/benchmark_math/BaseMetaPy.py
metaheuristicpy/continous/benchmark_math/BenchmarkFormulas.py
metaheuristicpy/continous/benchmark_math/EelGrouperOptimizer.py
metaheuristicpy/continous/benchmark_math/ExplorationEnchancedGreyWolfOptimizer.py
metaheuristicpy/continous/benchmark_math/GeneticAlgorithm.py
metaheuristicpy/continous/benchmark_math/GreaterCaneRatAlgorithm.py
metaheuristicpy/continous/benchmark_math/GreaterCaneRatAlgorithmOctave.py
metaheuristicpy/continous/benchmark_math/GreyWolfOptimizer.py
metaheuristicpy/continous/benchmark_math/InspiredGreyWolfOptimizer.py
metaheuristicpy/continous/benchmark_math/KomodoMlipirAlgorithm.py
metaheuristicpy/continous/benchmark_math/MemorybasedGreyWolfOptimizer.py
metaheuristicpy/continous/benchmark_math/MuskOxOptimizer.py
metaheuristicpy/continous/benchmark_math/ParticleSwarmOptimization.py
metaheuristicpy/continous/benchmark_math/SlimeMouldAlgorithm.py
metaheuristicpy/continous/benchmark_math/Utils.py
metaheuristicpy/continous/benchmark_math/WalrusOptimizationAlgorithm.py
metaheuristicpy/continous/benchmark_math/WhaleOptimizationAlgorithm.py
metaheuristicpy/continous/benchmark_math/__init__.py
metaheuristicpy/discrete/__init__.py
metaheuristicpy/discrete/feature_selection/ArchimedesOptimizationAlgorithm.py
metaheuristicpy/discrete/feature_selection/BaseMetaFeatureSelection.py
metaheuristicpy/discrete/feature_selection/EelGrouperOptimizer.py
metaheuristicpy/discrete/feature_selection/ExplorationEnhancedGreyWolfOptimizer.py
metaheuristicpy/discrete/feature_selection/GeneticAlgorithm.py
metaheuristicpy/discrete/feature_selection/GreaterCaneRatAlgorithm.py
metaheuristicpy/discrete/feature_selection/GreyWolfOptimizer.py
metaheuristicpy/discrete/feature_selection/MemoryBasedGreyWolfOptimizer.py
metaheuristicpy/discrete/feature_selection/ParticleSwarmOptimization.py
metaheuristicpy-3.1.0.dist-info/LICENSE
metaheuristicpy-3.1.0.dist-info/METADATA
metaheuristicpy-3.1.0.dist-info/WHEEL
metaheuristicpy-3.1.0.dist-info/top_level.txt
metaheuristicpy-3.1.0.dist-info/RECORD
