Metadata-Version: 2.1
Name: metaheuristicpy
Version: 3.1.0
Summary: A Python-based package of Metaheuristic Optimization Algorithms for Solving Continous and Discrete Optimization Problem
Author: I Made Satria Bimantara
Author-email: satriabimantara.imd@gmail.com
Keywords: Optimization,Metaheuristic,Swarm Intelligence,Evolutionary Algorithm,Soft Computing
Classifier: Development Status :: 4 - Beta
Classifier: Intended Audience :: Developers
Classifier: Intended Audience :: Science/Research
Classifier: License :: OSI Approved :: BSD License
Classifier: Framework :: Jupyter
Classifier: Programming Language :: Python :: 3
Classifier: Programming Language :: Python :: 3.8
Classifier: Operating System :: OS Independent
Classifier: Natural Language :: Indonesian
Classifier: Topic :: Scientific/Engineering :: Artificial Intelligence
Classifier: Topic :: Scientific/Engineering :: Mathematics
Requires-Python: >=3.8
License-File: LICENSE
Requires-Dist: pandas ==1.5.3
Requires-Dist: numpy ==1.24.2
Requires-Dist: openpyxl ==3.1.5
Requires-Dist: matplotlib ==3.6.3
Requires-Dist: seaborn ==0.11.1
Requires-Dist: scipy ==1.10.0
Requires-Dist: scikit-learn ==1.2.1
